<xml xmlns="http://www.w3.org/1999/xhtml"><block type="md_modules" id="uY-2#=]|0Z4-MzPg-#;n" x="13" y="-12"><statement name="MD_BLOCKS"><block type="mcookie_coreusb" id="Y*|*KMP;pO5~cEA)c|cu"><next><block type="mcookie_hub" id="d7N9(/E5:Uh*`=?S4PT."><value name="HUB07-8/9"><block type="mcookie_servo_setup" id="1;D#i#.vJhVqY`MSIv},"><field name="NAMETOPSERVO">TopServo</field><field name="NAMEBOTTOMSERVO">BottomServo</field><value name="SERVOTOPTYPE"><shadow type="mcookie_servo_type" id="H~)a:2Y5s=j3aB^|DZv`"><field name="SERVOTYPE">NOSERVO</field></shadow><block type="mcookie_servo_type" id="Iw+U8aB;Xf~e^^D2T]ZM"><field name="SERVOTYPE">180SERVO</field></block></value><value name="SERVOBOTTOMTYPE"><shadow type="mcookie_servo_type" id="ynN!)%ofGw25lJ3AlK:k"><field name="SERVOTYPE">NOSERVO</field></shadow></value></block></value></block></next></block></statement></block><block type="arduino_functions" id="3fW*^dkpM6]QF_%58Yh+" x="13" y="463"><statement name="LOOP_FUNC"><block type="controls_for" id="VjE!S@U,-Zdrly}7FQNN"><field name="VAR">i</field><value name="FROM"><block type="math_number" id="/sg!%Sg]fF+|4YV!ZtsG"><field name="NUM">0</field></block></value><value name="TO"><block type="math_number" id="t=^?)/XV9.^*9U-~Ln}i"><field name="NUM">90</field></block></value><value name="BY"><block type="math_number" id="?+|RsN5g/)y?RfFcC|Ba"><field name="NUM">10</field></block></value><statement name="DO"><block type="mcookie_servo_write" id="R=r}e8B1,)`^NXVS3#hS"><field name="SERVO_NAME">TopServo</field><value name="SERVO_ANGLE"><block type="variables_get" id="BKzItptct`Fv{*l_v`!o"><field name="VAR">i</field></block></value><next><block type="time_delay" id="8HVAazm19-jXmyL+O#34"><value name="DELAY_TIME_MILI"><block type="math_number" id=")2yB9l`QkNJ8V.16IL#J"><field name="NUM">20</field></block></value></block></next></block></statement><next><block type="controls_for" id="4c1[FddHg6k8rL?/0[Ne"><field name="VAR">i</field><value name="FROM"><block type="math_number" id="!}dbCIP3~h7PSXLFGWL`"><field name="NUM">90</field></block></value><value name="TO"><block type="math_number" id="QlrExY|K:3[`vF}X8z%?"><field name="NUM">0</field></block></value><value name="BY"><block type="math_number" id="z%k_0Hc)8Dt{RN5UU6b5"><field name="NUM">-10</field></block></value><statement name="DO"><block type="mcookie_servo_write" id="ff`u0Tcul4c4Lw_1*C}%"><field name="SERVO_NAME">TopServo</field><value name="SERVO_ANGLE"><block type="variables_get" id="g%Q]/GaohtiRnCj-Y0ph"><field name="VAR">i</field></block></value><next><block type="time_delay" id="e8194;H+nRW`CGlsmwZo"><value name="DELAY_TIME_MILI"><block type="math_number" id="cM=QNiONKS]nGLnP)kC?"><field name="NUM">20</field></block></value></block></next></block></statement></block></next></block></statement></block></xml>